drugname_standardizer/__init__.py
drugname_standardizer/__main__.py
drugname_standardizer/standardizer.py
drugname_standardizer/data/UNII_Names.txt
drugname_standardizer/data/UNII_dict.pkl
drugname_standardizer-1.2.7.dist-info/licenses/LICENSE
drugname_standardizer-1.2.7.dist-info/METADATA
drugname_standardizer-1.2.7.dist-info/WHEEL
drugname_standardizer-1.2.7.dist-info/entry_points.txt
drugname_standardizer-1.2.7.dist-info/top_level.txt
drugname_standardizer-1.2.7.dist-info/RECORD
