Metadata-Version: 2.4
Name: drugname_standardizer
Version: 1.2.7
Summary: A Python tool for standardizing drug names using the latest FDA's UNII Names list.
Author-email: Stéphanie Chevalier <pro.stephaniechevalier@gmail.com>
License: MIT
Project-URL: Homepage, https://github.com/StephanieChevalier/drugname_standardizer
Keywords: drug,synonyms,standardization,FDA,UNII
Classifier: Programming Language :: Python :: 3.12
Classifier: License :: OSI Approved :: MIT License
Classifier: Operating System :: OS Independent
Classifier: Topic :: Scientific/Engineering :: Bio-Informatics
Requires-Python: >=3.7
License-File: LICENSE
Requires-Dist: requests>=2
Requires-Dist: tqdm>=4
Dynamic: license-file
